biosigproc/__init__.py
biosigproc/common_utils.py
biosigproc/common_visualization.py
biosigproc/ecg/__init__.py
biosigproc/ecg/ecg_utils.py
biosigproc/eeg/__init__.py
biosigproc/eeg/eeg_utils.py
biosigproc/eeg/eeg_visualization.py
biosigproc/ppg/__init__.py
biosigproc/ppg/ppg_utils.py
biosigproc/ppg/ppg_visualization.py
BioSigProc-0.4.0.dist-info/LICENSE
BioSigProc-0.4.0.dist-info/METADATA
BioSigProc-0.4.0.dist-info/WHEEL
BioSigProc-0.4.0.dist-info/top_level.txt
BioSigProc-0.4.0.dist-info/RECORD
