Metadata-Version: 2.1
Name: BioSigProc
Version: 0.4.0
Summary: A package for processing and analyzing biomedical signals.
Home-page: https://github.com/gdeside/BioSigProc
Author: Guillaume Francois Deside
Author-email: guillaume.deside28@gmail.com
License: Apache Software License 2.0
Platform: UNKNOWN
Classifier: Development Status :: 3 - Alpha
Classifier: Intended Audience :: Developers
Classifier: Intended Audience :: Science/Research
Classifier: Programming Language :: Python :: 3
Classifier: Programming Language :: Python :: 3.6
Classifier: Programming Language :: Python :: 3.7
Classifier: Programming Language :: Python :: 3.8
Classifier: Programming Language :: Python :: 3.9
License-File: LICENSE
Requires-Dist: numpy
Requires-Dist: matplotlib
Requires-Dist: PyWavelets
